{
    "title": ["Tippspiel WM 2018"],
    "bets": ["Tipps"],
    "betgroups": ["Tippgruppen"],
    "players": ["Spieler"],
    "groups": ["Gruppen"],
    "rules": ["Regeln"],
    "admin": ["Admin"],
    "profile": ["Profil"],
    "logout": ["Logout"],
    "login": ["Login"],
    "register": ["Registrieren"],
    "changemail": ["Email Adresse ändern"],
    "updateprofile": ["Profil aktualisieren"],
    "update": ["Aktualisieren"],
    "changepassword": ["Passwort ändern"],
    "deleteprofile": ["Profil löschen"],
    "change": ["Ändern"],
    "mail": ["Mail-Adresse"],
    "score": ["Punkte"],
    "password": ["Passwort"],
    "passwordagain": ["Passwort erneut eingeben"],
    "passwordoptional": ["Passwort (optional)"],
    "passwordforconfirm": ["Passwort für Bestätigung"],
    "resetpassword": ["Passwort zurücksetzen"],
    "passwordnomatch": ["Passwörter stimmen nicht überein."],
    "password10chars": ["Passwort muss mindestens 10 Zeichen enthalten."],
    "username": ["Benutzername"],
    "newusername": ["Neuer Benutzername"],
    "newpassword": ["Neues Passwort"],
    "newmail": ["Neue Mail-Adresse"],
    "reminders": ["Erinnerungen"],
    "dailyResults": ["Tägliche Resultate"],
    "roles": ["Rollen"],
    "ROLE_USER": ["Benutzer"],
    "ROLE_ADMIN": ["Administrator"],
    "on": ["An"],
    "off": ["Aus"],

    "group": ["Gruppe"],
    "ro16": ["Achtelfinale"],
    "ro8": ["Viertelfinale"],
    "semifinals": ["Halbfinale"],
    "gameforthird": ["Spiel um Platz 3"],
    "finals": ["Finale"],

    "betstatistics": ["Tippstatistik"],
    "winner": ["Sieger"],
    "draw": ["Unentschieden"],
    "goalshome": ["Tore Heim"],
    "goalsguest": ["Tore Gast"],
    "goaldifference": ["Tordifferenz"],
    "total": ["Gesamt"],

    "points": ["Punkte"],
    "averagepoints": ["Punktedurchschnitt"],
    "saved": ["Gespeichert"],
    "notsaved": ["Nicht gespeichert"],
    "search": ["Suchen"],
    "name": ["Name"],
    "player": ["Spieler"],
    "joingroup": ["Gruppe beitreten"],
    "creategroup": ["Gruppe gründen"],
    "leavegroup": ["Gruppe verlassen"],
    "showbets": ["Tipps ansehen"],

    "betupdatesuccess": ["Wette aktualisiert"],
    "leavegroupsuccess": ["Gruppe erfolgreich verlassen"],
    "passwordresetsuccess": ["Passwort zurückgesetzt"],
    "logoutsuccess": ["Ausgeloggt"],
    "deleteprofilesuccess": ["Benutzer erfolgreich gelöscht"],

    "create": ["Erstellen"],

    "jek": ["Jekaterinburg"],
    "kal": ["Kaliningrad"],
    "kas": ["Kasan"],
    "nis": ["Nischni Nowgorod"],
    "mol": ["Moskau Luschniki"],
    "mos": ["Moskau Spartak"],
    "ros": ["Rostow am Don"],
    "sam": ["Samara"],
    "sar": ["Saransk"],
    "sot": ["Sotschi"],
    "san": ["Sankt Petersburg"],
    "wol": ["Wolgograd"],

    "rus": ["Russland"],
    "bel": ["Belgien"],
    "den": ["Dänemark"],
    "ger": ["Deutschland"],
    "eng": ["England"],
    "fra": ["Frankreich"],
    "ice": ["Island"],
    "cro": ["Kroatien"],
    "pol": ["Polen"],
    "por": ["Portugal"],
    "swe": ["Schweden"],
    "swi": ["Schweiz"],
    "ser": ["Serbien"],
    "spa": ["Spanien"],
    "arg": ["Argentinien"],
    "bra": ["Brasilien"],
    "col": ["Kolumbien"],
    "per": ["Peru"],
    "uru": ["Uruguay"],
    "egy": ["Ägypten"],
    "mor": ["Marokko"],
    "nig": ["Nigeria"],
    "sen": ["Senegal"],
    "tun": ["Tunesien"],
    "cos": ["Costa Rica"],
    "mex": ["Mexiko"],
    "pan": ["Panama"],
    "aus": ["Australien"],
    "ira": ["Iran"],
    "jap": ["Japan"],
    "sau": ["Saudi-Arabien"],
    "kor": ["Südkorea"],

    "tbd": ["Ausstehend"],

    "rule1": ["* Tippen nur bis vor Spielbeginn"],
    "rule2": ["* Tipps von anderen erst sichtbar wenn Spiel begonnen hat"],
    "rule3": ["* 5 Punkte bei korrektem Sieger Tipp"],
    "rule4": ["* 1 Punkt bei korrekter Anzahl Heim Tore"],
    "rule5": ["* 1 Punkt bei korrekter Anzahl Gast Tore"],
    "rule6": ["* 3 Punkte bei korrekter Tordifferenz (Sieger muss richtig sein)"],
    "rule7": ["* Als Spielstand für die Punktzahl Berechnung wird der Spielstand nach 90, resp. 120 Minuten verwendet. Elfmeterschiessen wird nicht berücksichtigt. Ein Unentschieden ist somit immer möglich."],
    "rule8": ["* Gruppenrangliste (Pro Spieltag wird ein Mittelwert gebildet (gerundet) und die Spieltageswerte anschließend zur Gesamtwertung der Gruppe addiert.)"],
    "rule9": ["Jeder Mitspieler kann eine Tippgruppe gründen. Einer Tippgruppe kann ein Passwort vergeben werden, dann kann dieser nur mit dem Passwort beigetreten werden. Möchte man die Tippgruppe öffentlich zugänglich machen, lässt man das Passwort weg. Für eine Tippgruppe braucht es mindestens drei Mitspieler, damit die Tippgruppe in der Rangliste erscheint. Die Tippgruppe ermöglicht eine Rangliste aller Mitspieler auf einen Blick. Es werden nur die Punkte der Mitglieder berücksichtigt, welche am jeweiligen Spieltag (nicht Kalendertag) auch schon Mitglied waren."]
}